PyGauss_Binomial/BinomialDistribution.py
PyGauss_Binomial/GaussianDistribution.py
PyGauss_Binomial/GeneralDistribution.py
PyGauss_Binomial/__init__.py
PyGauss_Binomial-1.0.0.dist-info/METADATA
PyGauss_Binomial-1.0.0.dist-info/WHEEL
PyGauss_Binomial-1.0.0.dist-info/top_level.txt
PyGauss_Binomial-1.0.0.dist-info/RECORD
