Metadata-Version: 2.1
Name: PyGauss-Binomial
Version: 1.0.0
Summary: Gaussian distributions and Binomial Distribution
Author: Mohammad Omar Adde
Author-email: mohaomar495@gmail.com
